domain/email/schemas.py
domain/email/service.py
flerity_core/__init__.py
flerity_core/config.py
flerity_core/py.typed
flerity_core/db/__init__.py
flerity_core/db/engine.py
flerity_core/db/rls.py
flerity_core/db/typing.py
flerity_core/db/uow.py
flerity_core/domain/__init__.py
flerity_core/domain/ai/__init__.py
flerity_core/domain/ai/bedrock_client.py
flerity_core/domain/ai/blocklist_repository.py
flerity_core/domain/ai/cache.py
flerity_core/domain/ai/conversation_analyzer.py
flerity_core/domain/ai/embedding_client.py
flerity_core/domain/ai/feedback_repository.py
flerity_core/domain/ai/feedback_schemas.py
flerity_core/domain/ai/feedback_service.py
flerity_core/domain/ai/feedback_vector_service.py
flerity_core/domain/ai/metrics.py
flerity_core/domain/ai/moderation.py
flerity_core/domain/ai/prompt_formatter.py
flerity_core/domain/ai/prompts_repository.py
flerity_core/domain/ai/rag_service.py
flerity_core/domain/ai/rate_limiter.py
flerity_core/domain/ai/repository.py
flerity_core/domain/ai/schemas.py
flerity_core/domain/ai/service.py
flerity_core/domain/ai/service_updated.py
flerity_core/domain/ai/service_with_formatter.py
flerity_core/domain/analytics/__init__.py
flerity_core/domain/analytics/cache.py
flerity_core/domain/analytics/repository.py
flerity_core/domain/analytics/schemas.py
flerity_core/domain/analytics/scoring.py
flerity_core/domain/analytics/service.py
flerity_core/domain/auth/repository.py
flerity_core/domain/auth/schemas.py
flerity_core/domain/auth/service.py
flerity_core/domain/auth/social_validators.py
flerity_core/domain/catalogs/__init__.py
flerity_core/domain/catalogs/repository.py
flerity_core/domain/catalogs/schemas.py
flerity_core/domain/catalogs/service.py
flerity_core/domain/devices/repository.py
flerity_core/domain/devices/schemas.py
flerity_core/domain/devices/service.py
flerity_core/domain/integrations/__init__.py
flerity_core/domain/integrations/repository.py
flerity_core/domain/integrations/schemas.py
flerity_core-0.1.2.dev20251117215438.dist-info/licenses/LICENSE
flerity_core-0.1.2.dev20251117215438.dist-info/METADATA
flerity_core-0.1.2.dev20251117215438.dist-info/WHEEL
flerity_core-0.1.2.dev20251117215438.dist-info/top_level.txt
flerity_core-0.1.2.dev20251117215438.dist-info/RECORD
