Metadata-Version: 2.4
Name: flerity-core
Version: 0.1.2.dev20251117215438
Summary: Flerity shared core library
Requires-Python: >=3.11
License-File: LICENSE
Requires-Dist: sqlalchemy[asyncio]>=2.0.44
Requires-Dist: asyncpg>=0.30.0
Requires-Dist: pydantic>=2.12.4
Requires-Dist: pydantic[email]>=2.12.4
Requires-Dist: pydantic-settings>=2.12.0
Requires-Dist: fastapi>=0.121.2
Requires-Dist: redis>=7.0.1
Requires-Dist: httpx==0.28.1
Requires-Dist: requests>=2.31.0
Requires-Dist: structlog>=25.5.0
Requires-Dist: cryptography>=46.0.3
Requires-Dist: python-dateutil>=2.9.0.post0
Requires-Dist: pytz>=2025.2
Requires-Dist: boto3<1.40.62,>=1.40.61
Requires-Dist: aioboto3>=15.5.0
Requires-Dist: aio-pika>=9.5.8
Requires-Dist: opentelemetry-api>=1.38.0
Requires-Dist: opentelemetry-sdk>=1.38.0
Requires-Dist: opentelemetry-instrumentation-fastapi>=0.42b0
Requires-Dist: opentelemetry-instrumentation-redis>=0.42b0
Requires-Dist: opentelemetry-instrumentation-sqlalchemy>=0.42b0
Requires-Dist: opentelemetry-exporter-otlp-proto-grpc>=1.38.0
Requires-Dist: sentry-sdk[fastapi]>=2.44.0
Requires-Dist: aiohttp>=3.13.2
Requires-Dist: python-multipart>=0.0.20
Requires-Dist: python-jose[cryptography]>=3.5.0
Requires-Dist: PyJWT>=2.10.1
Requires-Dist: bcrypt>=5.0.0
Provides-Extra: dev
Requires-Dist: pytest>=9.0.1; extra == "dev"
Requires-Dist: pytest-asyncio>=1.3.0; extra == "dev"
Requires-Dist: pytest-cov>=7.0.0; extra == "dev"
Requires-Dist: pytest-mock>=3.15.1; extra == "dev"
Requires-Dist: mypy>=1.18.2; extra == "dev"
Requires-Dist: ruff>=0.14.5; extra == "dev"
Requires-Dist: black>=25.11.0; extra == "dev"
Requires-Dist: httpx==0.28.1; extra == "dev"
Requires-Dist: testcontainers>=4.13.3; extra == "dev"
Requires-Dist: faker>=38.0.0; extra == "dev"
Dynamic: license-file
Dynamic: requires-python
